AUTHORS
LICENSE
MANIFEST.in
README.rst
setup.py
aloha_editor/__init__.py
aloha_editor/urls.py
aloha_editor/views.py
aloha_editor/templates/aloha_editor/css.html
aloha_editor/templates/aloha_editor/js.html
aloha_editor/templatetags/__init__.py
aloha_editor/templatetags/aloha_editor.py
django_aloha_editor.egg-info/PKG-INFO
django_aloha_editor.egg-info/SOURCES.txt
django_aloha_editor.egg-info/dependency_links.txt
django_aloha_editor.egg-info/not-zip-safe
django_aloha_editor.egg-info/top_level.txt