Metadata-Version: 1.1
Name: django-aloha-editor
Version: 1.1.0
Summary: A set of project independent reusable features.
Home-page: http://github.com/baskoopmans/django-aloha-editor/
Author: Bas Koopmans
Author-email: e-mail@baskoopmans.nl
License: BSD
Download-URL: http://github.com/baskoopmans/django-aloha-editor/downloads
Platform: UNKNOWN
Classifier: Development Status :: 4 - Beta
Classifier: Environment :: Web Environment
Classifier: Framework :: Django
Classifier: Intended Audience :: Developers
Classifier: License :: OSI Approved :: BSD License
Classifier: Operating System :: OS Independent
Classifier: Programming Language :: Python
Classifier: Topic :: Software Development :: Libraries :: Python Modules
